cysimdjson/cysimdjson.cpython-311-x86_64-linux-gnu.so
cysimdjson/cysimdjsonc.h
cysimdjson/jsoninter.h
cysimdjson/cysimdjson.h
cysimdjson/__init__.py
cysimdjson/cysimdjson.pyx
cysimdjson/pysimdjson/errors.h
cysimdjson/simdjson/simdjson.h
cysimdjson-24.12.dist-info/top_level.txt
cysimdjson-24.12.dist-info/METADATA
cysimdjson-24.12.dist-info/WHEEL
cysimdjson-24.12.dist-info/RECORD
cysimdjson-24.12.dist-info/LICENSE
