Metadata-Version: 2.1
Name: cysimdjson
Version: 24.12
Summary: High-speed JSON parser
Home-page: https://github.com/TeskaLabs/cysimdjson
Author: TeskaLabs Ltd
Author-email: info@teskalabs.com
Project-URL: Source, https://github.com/TeskaLabs/cysimdjson
Project-URL: Tracker, https://github.com/TeskaLabs/cysimdjson/issues
Platform: any
Classifier: Development Status :: 5 - Production/Stable
Classifier: License :: OSI Approved :: Apache Software License
Classifier: Programming Language :: Python :: 3.6
Classifier: Programming Language :: Python :: 3.7
Classifier: Programming Language :: Python :: 3.8
Classifier: Programming Language :: Python :: 3.9
Classifier: Programming Language :: Python :: 3.10
Classifier: Programming Language :: Python :: 3.11
Classifier: Programming Language :: Python :: 3.12
Classifier: Operating System :: Microsoft :: Windows
Classifier: Operating System :: POSIX :: Linux
Classifier: Operating System :: MacOS :: MacOS X
License-File: LICENSE
